zeroguard/__init__.py
zeroguard/__version__.py
zeroguard-0.0.1.dev2.dist-info/METADATA
zeroguard-0.0.1.dev2.dist-info/WHEEL
zeroguard-0.0.1.dev2.dist-info/top_level.txt
zeroguard-0.0.1.dev2.dist-info/RECORD
